Metadata-Version: 1.1
Name: djorm-pgarray
Version: 1.0
Summary: PostgreSQL native array fields extension for Django.
Home-page: https://github.com/niwibe/djorm-pgarray
Author: Andrey Antukh
Author-email: niwi@niwi.be
License: BSD
Platform: OS Independent
Classifier: Development Status :: 4 - Beta
Classifier: Framework :: Django
Classifier: Intended Audience :: Developers
Classifier: License :: OSI Approved :: BSD License
Classifier: Operating System :: OS Independent
Classifier: Programming Language :: Python
Classifier: Programming Language :: Python :: 2
Classifier: Programming Language :: Python :: 2.7
Classifier: Programming Language :: Python :: 3
Classifier: Programming Language :: Python :: 3.3
Classifier: Programming Language :: Python :: 3.4
Classifier: Topic :: Internet :: WWW/HTTP
